app/__init__.py
app/init.py
app/main.py
app/config/__init__.py
app/config/config.py
app/queue/__init__.py
app/queue/queue_consumer.py
app/queues/__init__.py
app/queues/queue_consumer.py
app/scripts/__init__.py
app/scripts/rerun_task.sh
app/scripts/run_task.sh
app/scripts/run_verify_task.sh
app/scripts/stop_task.sh
app/scripts/stop_verify_task.sh
app/service/__init__.py
app/service/curl_service.py
app/service/export_policy_as_onnx.py
app/service/message_service.py
app/service/task_service.py
app/service/thread_manage.py
app/service/util_service.py
coldplay_agent-0.2.0.dist-info/METADATA
coldplay_agent-0.2.0.dist-info/WHEEL
coldplay_agent-0.2.0.dist-info/entry_points.txt
coldplay_agent-0.2.0.dist-info/top_level.txt
coldplay_agent-0.2.0.dist-info/RECORD
