Metadata-Version: 2.1
Name: coldplay_agent
Version: 0.2.0
Summary: coldplay agent package
Home-page: https://github.com/zoie438730732/limx-coldplay-agent
Author: Joey
Author-email: joeym@limxdynamics.com
Classifier: Programming Language :: Python :: 3
Classifier: License :: OSI Approved :: MIT License
Classifier: Operating System :: OS Independent
Requires-Python: >=3.10
Requires-Dist: pika==1.3.2
Requires-Dist: requests==2.31.0
Requires-Dist: pysmb==1.2.10
Requires-Dist: influxdb-client==1.47.0
